{
	"name": "colisioncable6_1",
	"plugin-id": "Sprite",
	"sid": 987831806290977,
	"isGlobal": false,
	"instanceVariables": [],
	"behaviorTypes": [
		{
			"behaviorId": "DragnDrop",
			"name": "ArrastrarYSoltar",
			"sid": 113387726280482
		}
	],
	"effectTypes": [],
	"animations": {
		"items": [
			{
				"frames": [
					{
						"width": 7,
						"height": 6,
						"originX": 0.42857142857142855,
						"originY": 0.8333333333333334,
						"originalSource": "",
						"exportFormat": "lossless",
						"exportQuality": 0.8,
						"imageSpriteId": 5493253,
						"useCollisionPoly": true,
						"duration": 1,
						"tag": ""
					}
				],
				"sid": 369889110175667,
				"name": "Animation 1",
				"isLooping": false,
				"isPingPong": false,
				"repeatCount": 1,
				"repeatTo": 0,
				"speed": 5
			}
		],
		"subfolders": []
	}
}